VenomousPredator/__init__.py
VenomousPredator/akdfjshia.py
VenomousPredator/algorithms.py
VenomousPredator/fsj.py
VenomousPredator/luu.py
VenomousPredator/sjdậke.py
VenomousPredator/skibidi toilet.py
VenomousPredator/utils.py
venomouspredator-1.4.1.dist-info/licenses/LICENSE.txt
venomouspredator-1.4.1.dist-info/METADATA
venomouspredator-1.4.1.dist-info/WHEEL
venomouspredator-1.4.1.dist-info/top_level.txt
venomouspredator-1.4.1.dist-info/RECORD
