Metadata-Version: 2.4
Name: VenomousPredator
Version: 1.4.1
Summary: A library of elementary level algorithms
Author-email: hoducminh <rezenela1308@email.com>
Project-URL: Homepage, https://github.com/yourname/mylib
Project-URL: Source, https://github.com/yourname/mylib
Project-URL: Tracker, https://github.com/yourname/mylib/issues
Keywords: algorithms,graph,dijkstra,python
Classifier: Programming Language :: Python :: 3
Classifier: License :: OSI Approved :: MIT License
Classifier: Operating System :: OS Independent
Requires-Python: >=3.8
License-File: LICENSE.txt
Dynamic: license-file
